setup.py
coretalk/__init__.py
coretalk/app.py
coretalk/settings.py
coretalk/urls.py
coretalk/wsgi.py
coretalk.egg-info/PKG-INFO
coretalk.egg-info/SOURCES.txt
coretalk.egg-info/dependency_links.txt
coretalk.egg-info/requires.txt
coretalk.egg-info/top_level.txt
coretalk/models/__init__.py
coretalk/models/coretalk/__init__.py
coretalk/models/coretalk/sshkey.py
coretalk/models/coretalk/userdata.py
coretalk/views/__init__.py
coretalk/views/api/__init__.py
coretalk/views/api/sshkey.py
coretalk/views/api/userdata.py
coretalk/views/cloudinit/__init__.py
coretalk/views/cloudinit/functions.py