Metadata-Version: 1.1
Name: coretalk
Version: 17.4.1
Summary: CloudInit support for CoreCluster IaaS
Home-page: http://cloudover.org/coretalk/
Author: Marta and Maciej Nabozny
Author-email: marta.nabozny@gmail.com
License: UNKNOWN
Download-URL: https://github.com/cloudOver/CoreTalk/archive/master.zip
Keywords: corecluster,cloudover,cloud,cloudinit
Platform: UNKNOWN
